luxport/luxport/__init__.py
luxport/luxport/cli.py
luxport/luxport/downloader.py
luxport/luxport/exporter.py
luxport/luxport/lux_parser.py
luxport/luxport/utils.py
luxport-0.1.5.dist-info/licenses/LICENSE
luxport-0.1.5.dist-info/METADATA
luxport-0.1.5.dist-info/WHEEL
luxport-0.1.5.dist-info/entry_points.txt
luxport-0.1.5.dist-info/top_level.txt
luxport-0.1.5.dist-info/RECORD
