Metadata-Version: 2.4
Name: luxport
Version: 0.1.5
Summary: A utility for exporting IIIF manifest data to ZIP files
Author: William J.B. Mattingly
Author-email: "William J.B. Mattingly" <william.mattingly@yale.edu>
License: MIT
Project-URL: Homepage, https://github.com/project-lux/luxport
Project-URL: Bug Tracker, https://github.com/project-lux/luxport/issues
Project-URL: Documentation, https://github.com/project-lux/luxport#readme
Project-URL: Source Code, https://github.com/project-lux/luxport
Keywords: iiif,manifest,export,yale,library,zip
Classifier: Programming Language :: Python :: 3
Classifier: Programming Language :: Python :: 3.7
Classifier: Programming Language :: Python :: 3.8
Classifier: Programming Language :: Python :: 3.9
Classifier: Programming Language :: Python :: 3.10
Classifier: License :: OSI Approved :: MIT License
Classifier: Operating System :: OS Independent
Classifier: Development Status :: 4 - Beta
Classifier: Intended Audience :: Developers
Classifier: Intended Audience :: Education
Classifier: Intended Audience :: Science/Research
Classifier: Topic :: Software Development :: Libraries :: Python Modules
Classifier: Topic :: Utilities
Requires-Python: >=3.7
License-File: LICENSE
Requires-Dist: requests>=2.25.0
Requires-Dist: tqdm>=4.62.0
Requires-Dist: jsonschema>=4.0.0
Dynamic: author
Dynamic: license-file
Dynamic: requires-python
